{
  "oscilacao": [
    {
      "id": 1,
      "uploadDate": "2022-10-16T024731.311Z",
      "geom": {
        "lat": 22.22,
        "long": 21,
        "alt": 749
      }
    },
    {
      "id": 2,
      "uploadDate": "2022-10-16T024731.311Z",
      "geom": {
        "lat": 22.22,
        "long": 21,
        "alt": 749
      }
    },
    {
      "id": 3,
      "uploadDate": "2022-10-16T024731.311Z",
      "geom": {
        "lat": 22.22,
        "long": 21,
        "alt": 749
      }
    },
    {
      "uploadDate": "2022-10-16T024731.311Z",
      "geom": {
        "lat": 22.22,
        "long": 21,
        "alt": 749
      },
      "id": 4
    },
    {
      "uploadDate": "2022-10-16T024731.311Z",
      "geom": {
        "lat": 22.22,
        "long": 21,
        "alt": 749
      },
      "id": 5
    },
    {
      "uploadDate": "2022-10-16T024731.311Z",
      "geom": {
        "lat": 22.22,
        "long": 21,
        "alt": 749
      },
      "id": 6
    }
  ]
}